officebots/__init__.py
officebots/officebots.py
officebots-0.1.0.data/scripts/officebots-ros
officebots-0.1.0.dist-info/METADATA
officebots-0.1.0.dist-info/WHEEL
officebots-0.1.0.dist-info/top_level.txt
officebots-0.1.0.dist-info/RECORD
